geode_simplexremesh/Geode-SimplexRemesh_brep.dll
geode_simplexremesh/Geode-SimplexRemesh_core.dll
geode_simplexremesh/Geode-SimplexRemesh_corner.dll
geode_simplexremesh/Geode-SimplexRemesh_line2d.dll
geode_simplexremesh/Geode-SimplexRemesh_line3d.dll
geode_simplexremesh/Geode-SimplexRemesh_line_common.dll
geode_simplexremesh/Geode-SimplexRemesh_metric.dll
geode_simplexremesh/Geode-SimplexRemesh_section.dll
geode_simplexremesh/Geode-SimplexRemesh_solid.dll
geode_simplexremesh/Geode-SimplexRemesh_surface2d.dll
geode_simplexremesh/Geode-SimplexRemesh_surface3d.dll
geode_simplexremesh/Geode-SimplexRemesh_surface_common.dll
geode_simplexremesh/__init__.py
geode_simplexremesh/brep.py
geode_simplexremesh/concrt140.dll
geode_simplexremesh/geode_simplexremesh.py
geode_simplexremesh/geode_simplexremesh_brep.py
geode_simplexremesh/geode_simplexremesh_metric.py
geode_simplexremesh/geode_simplexremesh_py_brep.pyd
geode_simplexremesh/geode_simplexremesh_py_metric.pyd
geode_simplexremesh/geode_simplexremesh_py_section.pyd
geode_simplexremesh/geode_simplexremesh_section.py
geode_simplexremesh/metric.py
geode_simplexremesh/msvcp140.dll
geode_simplexremesh/msvcp140_1.dll
geode_simplexremesh/msvcp140_2.dll
geode_simplexremesh/msvcp140_atomic_wait.dll
geode_simplexremesh/msvcp140_codecvt_ids.dll
geode_simplexremesh/section.py
geode_simplexremesh/vcruntime140.dll
geode_simplexremesh/vcruntime140_1.dll
Geode_SimplexRemesh-5.2.11.dist-info/METADATA
Geode_SimplexRemesh-5.2.11.dist-info/WHEEL
Geode_SimplexRemesh-5.2.11.dist-info/top_level.txt
Geode_SimplexRemesh-5.2.11.dist-info/RECORD
