Metadata-Version: 2.1
Name: Geode-SimplexRemesh
Version: 5.2.11
Summary: Simplex remeshing Geode-solutions OpenGeode module
Home-page: https://github.com/Geode-solutions/Geode-SimplexRemesh
Author: Geode-solutions
Author-email: contact@geode-solutions.com
License: Proprietary
Platform: UNKNOWN
